efb_notice_middleware/__init__.py
efb_notice_middleware/__version__.py
efb_notice_middleware-0.0.6.dist-info/LICENSE
efb_notice_middleware-0.0.6.dist-info/METADATA
efb_notice_middleware-0.0.6.dist-info/WHEEL
efb_notice_middleware-0.0.6.dist-info/entry_points.txt
efb_notice_middleware-0.0.6.dist-info/top_level.txt
efb_notice_middleware-0.0.6.dist-info/RECORD
