Metadata-Version: 2.1
Name: efb-notice-middleware
Version: 0.0.6
Summary: Notice middleware for EH Forwarder Bot, notice and tag messages.
Home-page: https://github.com/efb-middleware/notice
Author: WolfSilver
Author-email: aexou@outlook.com
License: AGPLv3+
Keywords: ehforwarderbot,EH Forwarder Bot,EH Forwarder Bot Middleware,Notice,Tag
Platform: UNKNOWN
Classifier: Development Status :: 3 - Alpha
Classifier: License :: OSI Approved :: GNU Affero General Public License v3 or later (AGPLv3+)
Classifier: Intended Audience :: Developers
Classifier: Intended Audience :: End Users/Desktop
Classifier: Programming Language :: Python :: 3 :: Only
Classifier: Programming Language :: Python :: 3.6
Classifier: Programming Language :: Python :: 3.7
Classifier: Topic :: Communications :: Chat
Classifier: Topic :: Utilities
Requires-Python: >=3.6
Requires-Dist: ehforwarderbot
Requires-Dist: PyYaml
